Metadata-Version: 2.2
Name: tensorg
Version: 0.1.10
Summary: Tensor Network Library with Symbolic Autograd
Author-email: Thomas Ahle <lobais@gmail.com>
License:                     GNU AFFERO GENERAL PUBLIC LICENSE
Project-URL: Homepage, https://tensorcookbook.com
Project-URL: Repository, https://github.com/thomasahle/tensorgrad.git
Project-URL: Issues, https://github.com/thomasahle/tensorgrad/issues
Keywords: tensors,autograd
Classifier: Development Status :: 4 - Beta
Classifier: Programming Language :: Python
Requires-Python: >=3.10
License-File: LICENSE
Requires-Dist: networkx==3.2.1
Requires-Dist: numpy
Requires-Dist: torch
Requires-Dist: nbval
Requires-Dist: pytest
Requires-Dist: einops
Requires-Dist: pdf2image
Requires-Dist: sympy
Requires-Dist: sparse
Requires-Dist: opt_einsum
